djangocms_haystack/__init__.py
djangocms_haystack/apps.py
djangocms_haystack/base.py
djangocms_haystack/helpers.py
djangocms_haystack/search_indexes.py
djangocms_haystack/templates/djangocms_haystack/base.html
djangocms_haystack/templates/djangocms_haystack/form.html
djangocms_haystack/templates/djangocms_haystack/pagination.html
djangocms_haystack/templates/djangocms_haystack/results.html
djangocms_haystack/templates/djangocms_haystack/search.html
djangocms_haystack/urls.py
djangocms_haystack/views.py
djangocms_haystack-0.4.1.dist-info/METADATA
djangocms_haystack-0.4.1.dist-info/WHEEL
djangocms_haystack-0.4.1.dist-info/RECORD
